<?xml version="1.0" encoding="UTF-8"?>

<root>
    <str key="4261555918" type="ucdt">战区统帅</str>
    <str key="4261582970" type="ucdt">AF-22乌鸦：奥星勋章</str>
    <str key="4261590000" type="ucdt">VOID载具贴花</str>
    <str key="4261685177" type="ucdt">自动充能器</str>
    <str key="4261752191" type="ucdt">默认弹匣的弹药容量增加38发。</str>
    <str key="4262140088" type="ucdt">NC机首炮[主武器]</str>
    <str key="4262154511" type="ugdt">Hubcaps VS005 (DNT)</str>
    <str key="4262272756" type="ucdt">NSX政宗：铜质勋章</str>
    <str key="4262283248" type="ucdt">用Defector赢得20次击杀。</str>
    <str key="4262293819" type="ucdt">怨恨头盔</str>
    <str key="4262405889" type="ucdt">纳能爱国者烟花枪</str>
    <str key="4262449317" type="ucdt">TSAR-42</str>
    <str key="4262488668" type="ucdt">弹药携带量 3</str>
    <str key="4262727921" type="ucdt">吸血鬼 5</str>
    <str key="4262735498" type="ucdt">装弹速率 1</str>
    <str key="4262782886" type="ucdt">我们正在寻找前线战士来阻击敌方载具并攻破他们的防御工事。所以，锁定并装载你的火箭发射器，作为一名Heavy Assault前往最近的战场报到，和你的队伍一起，协助攻入敌方基地。&lt;br&gt;&lt;/br&gt;&lt;br&gt;&lt;/br&gt;必须作为Heavy Assault完成目标。</str>
    <str key="4262915068" type="ucdt">合成公式一览</str>
    <str key="4262940470" type="ucdt">手柄 %d 轴向 Z+ 轴向</str>
    <str key="4263046251" type="ucdt">腐蚀烟雾 1</str>
    <str key="4263106444" type="ucdt">战果绶带</str>
    <str key="4263227772" type="ucdt">切换到渗透者（可选）</str>
    <str key="4263266364" type="ucdt">当战斗医疗兵驾乘载具时，可以被动地治疗5米范围内的友军士兵，每秒恢复10点生命值。</str>
    <str key="4263322593" type="ucdt">&lt;font color="#00FFAA"&gt;Foster：&lt;/font&gt;更多的不稳定正发生在Esamir的表面下，而Warpgate自那时起一直有……操作问题。</str>
    <str key="4263403898" type="ugdt">Mending Field 3</str>
    <str key="4263536462" type="ucdt">为你的载具添加贴花。所有阵营均可使用此贴花。</str>
    <str key="4263548653" type="ucdt">纳能网生成器 5</str>
    <str key="4263587661" type="ucdt">快速退出 2</str>
    <str key="4263676969" type="ucdt">“头等奖”纳能毁灭者：铜质勋章</str>
    <str key="4263696015" type="ucdt">信用卡安全码</str>
    <str key="4263859436" type="ugdt">NC-I001标准头盔</str>
    <str key="4263954555" type="ucdt">电子干扰套装 3</str>
    <str key="4264107380" type="ucdt">该武器发射单枚弹头，伤害和速度增加，但射速减慢20%。</str>
    <str key="4264154119" type="ucdt">复合装甲升级礼包</str>
    <str key="4264265607" type="ucdt">TRAC-5 S进一步加强了卡宾枪的多样性，它可以根据目标的远近来选择不同的射击模式。仅限地球共和国使用。</str>
    <str key="4264281018" type="ucdt">VE68“海神”采用了超频设计，射击速度奇快，在近距离战斗中可以提供完美的火力。</str>
    <str key="4264435242" type="ucdt">手持近战武器击杀一名敌人会回复175点生命值，快速出刀不会触发此效果。</str>
    <str key="4264650544" type="ucdt">动量护甲 3</str>
    <str key="4264654401" type="ucdt">TR-CMG25</str>
    <str key="4264693486" type="ucdt">占领三叉戟</str>
    <str key="4264888953" type="ucdt">消音器</str>
    <str key="4264940382" type="ucdt">当前等级：%0 / %1</str>
    <str key="4264957833" type="ucdt">在你的载具上添加因达尔沙丘迷彩图案。所有阵营均可使用此装备。</str>
    <str key="4264985704" type="ucdt">因达尔海床护甲迷彩</str>
    <str key="4265033956" type="ucdt">提升武器的有效射程</str>
    <str key="4265038308" type="ugdt">隐身猎手 2</str>
    <str key="4265235179" type="ucdt">轰天雷XS：金质勋章</str>
    <str key="4265644648" type="ucdt">武器的装弹时间减少0.6秒。</str>
    <str key="4265656233" type="ucdt">弗雷尔监控场 [C]</str>
    <str key="4265868756" type="ucdt">Metabolism 3 (11053) (DNT)</str>
    <str key="4265929519" type="ucdt">艾美瑞什生物实验室占领状态</str>
    <str key="4266316546" type="ucdt">镶边黑色护甲迷彩</str>
    <str key="4266429036" type="ucdt">接受一个任务以开始。</str>
    <str key="4266546693" type="ucdt">将闪电的获取时间间隔减少300秒</str>
    <str key="4266767826" type="ucdt">音乐音量</str>
    <str key="4266918659" type="ucdt">默认准星</str>
    <str key="4266944045" type="ucdt">启示录：奥星勋章</str>
    <str key="4266955332" type="ucdt">地球共和国RASK III型 + 证书点</str>
    <str key="4267091053" type="ucdt">在整个十月期间，以超棒的价格来入手你最爱的骇人物品吧！</str>
    <str key="4267092892" type="ucdt">TR工程兵11C</str>
    <str key="4267175944" type="ugdt">Roll Rate 3</str>
    <str key="4267591215" type="ucdt">武器的装弹时间减少0.2秒。</str>
    <str key="4267637156" type="ucdt">i3fs护甲贴花</str>
    <str key="4267655749" type="ucdt">决裂者炫光镶边</str>
    <str key="4267694128" type="ucdt">心动折扣，尽享最热销突袭者武器！</str>
    <str key="4267694987" type="ucdt">弹药携带量 1</str>
    <str key="4267780811" type="ucdt">先驱保险杠002描述</str>
    <str key="4267829184" type="ucdt">捣乱者轮胎钉</str>
    <str key="4267940082" type="ucdt">座无虚席武器迷彩</str>
    <str key="4268457141" type="ucdt">C-4：奥星勋章</str>
    <str key="4268679945" type="ucdt">RMR-4</str>
    <str key="4268690007" type="ucdt">将银河的获取时间间隔减少至18.5分钟。</str>
    <str key="4268913735" type="ucdt">受到来自步兵轻武器和载具机枪的伤害降低10%，爆炸伤害额外降低38%，穿甲机枪的伤害额外降低35%，飞机机炮的伤害额外降低37%，C-4的伤害加成降低100%。</str>
    <str key="4268988851" type="ucdt">70证书点</str>
    <str key="4269001402" type="ucdt">分组错误，无法移交火力小组指挥权。</str>
    <str key="4269187275" type="ucdt">武器能够携带的最大弹药数量增加200发。</str>
    <str key="4269197730" type="ugdt">ANT Ghoulish Horn</str>
    <str key="4269323169" type="ucdt">炫光镶边</str>
    <str key="4269394104" type="ucdt">决裂者M20蛇蜥[尾部武器]</str>
    <str key="4269404473" type="ucdt">充能 4</str>
    <str key="4269505983" type="ucdt">M18穿刺者</str>
    <str key="4269887241" type="ucdt">伏击手喷射背包能提供短暂的爆发推力，将使用者快速向前推进，而垂直高度提升有限。使用后有6秒冷却时间。</str>
    <str key="4269903873" type="ucdt">发现共和国军队！</str>
    <str key="4269924826" type="ucdt">拆解者 5</str>
    <str key="4269934869" type="ugdt">VBD载具贴花</str>
    <str key="4269959601" type="ugdt">v0.4.0</str>
    <str key="4270036635" type="ucdt">无法将该小队从连队中移除。</str>
    <str key="4270125905" type="ugdt">The Swarm Armor Decal</str>
    <str key="4270135790" type="ucdt">武器的装弹时间减少0.5秒。</str>
    <str key="4270212737" type="ucdt">甲小队路标点</str>
    <str key="4270407749" type="ucdt">TRAC-5 S：银质勋章</str>
    <str key="4270434311" type="ucdt">“链接”薙刀：银质勋章</str>
    <str key="4270444659" type="ucdt">守卫</str>
    <str key="4270671381" type="ucdt">受到来自轻武器和重机枪的伤害降低20%。</str>
    <str key="4270677378" type="ugdt">Harasser Speed Freak Bumper</str>
    <str key="4270715459" type="ucdt">无法解散连队。</str>
    <str key="4270733889" type="ucdt">机首炮</str>
    <str key="4270805282" type="ucdt">O字贴花</str>
    <str key="4270856153" type="ucdt">红色弱</str>
    <str key="4271098857" type="ucdt">武器能够携带的最大榴弹数量增加48发。</str>
    <str key="4271112262" type="ucdt">铂金NS-357P二老板绶带
铂金NS-357P二老板绶带</str>
    <str key="4271208383" type="ucdt">安全卫士</str>
    <str key="4271224314" type="ucdt">建筑物防御套装</str>
    <str key="4271262938" type="ugdt">NC Holiday Hat</str>
    <str key="4271306673" type="ucdt">为你的驾驶舱增添个性化装饰，在座舱玻璃处加上地球共和国标志贴花。仅限地球共和国使用。</str>
    <str key="4271533490" type="ucdt">个人获得的经验增加10%。</str>
    <str key="4271549058" type="ucdt">默认弹匣的弹药容量增加4发。</str>
    <str key="4271559561" type="ucdt">地球共和国</str>
    <str key="4271567233" type="ucdt">在你的护甲上添加一次性热带丛林迷彩图案。仅限地球共和国使用。一次性迷彩只能在本角色的一套配置中应用一次。</str>
    <str key="4271605357" type="ucdt">MAX铁拳：银质勋章</str>
    <str key="4271611120" type="ucdt">九</str>
    <str key="4271617800" type="ucdt">M20幼龙：金质勋章</str>
    <str key="4271692230" type="ucdt">螳螂头盔</str>
    <str key="4271746060" type="ucdt">工蚁和决裂者的纳能消耗降低20%。</str>
    <str key="4271758447" type="ucdt">TR_Male_Standard_NPC_Radio</str>
    <str key="4271861943" type="ucdt">先驱：功能插槽</str>
    <str key="4271953073" type="ucdt">关闭此功能将取消显示当前活动语音聊天列表。（默认：开）</str>
    <str key="4272002814" type="ugdt">DIGT载具贴花</str>
    <str key="4272030434" type="ucdt">霍森中立区域</str>
    <str key="4272059589" type="ucdt">顾问</str>
    <str key="4272190484" type="ucdt">东北台地</str>
    <str key="4272252291" type="ucdt">希尔赫斯.小型哨所.15</str>
    <str key="4272253880" type="ucdt">NS-60火焰喷射器：金质勋章</str>
    <str key="4272355113" type="ucdt">向MAX机甲中灌输不稳定的能量，持续20秒，提升10%最大伤害输出并小幅提升移动速度，但是受到的伤害会增加20%。</str>
    <str key="4272394166" type="ucdt">T32公牛：金质勋章</str>
    <str key="4272423369" type="ucdt">本影头盔</str>
    <str key="4272553242" type="ucdt">&lt;font color="#00FFAA"&gt;FL-34：&lt;/font&gt;怎么样，伙计，够刺激吧。</str>
    <str key="4272602806" type="ucdt">军团</str>
    <str key="4272619393" type="ucdt">NSX兜</str>
    <str key="4272731980" type="ucdt">武器能够携带的最大弹药数量增加700发。</str>
    <str key="4272740350" type="ucdt">XMG-ARX Galilei银质勋章</str>
    <str key="4272837023" type="ugdt">粒子迷彩</str>
    <str key="4272943436" type="ucdt">女武神</str>
    <str key="4272952628" type="ucdt">&lt;font color="#00FFAA"&gt;Umatherin最高长官：&lt;/font&gt;这里为什么会有一张Veridian Genetics的钥匙卡？有研究人员是信徒吗？你应该马上回到地下基地，看看这把钥匙是用在哪儿的。</str>
    <str key="4272959258" type="ucdt">查看</str>
    <str key="4273343423" type="ucdt">起飞战斗机</str>
    <str key="4273473587" type="ugdt">Glass Material Platform</str>
    <str key="4273477928" type="ucdt">口径 3</str>
    <str key="4273599701" type="ucdt">加强部署护盾 6</str>
    <str key="4273725388" type="ucdt">泰坦150高爆破甲炮</str>
    <str key="4273933736" type="ucdt">&lt;font color="#dc9c36"&gt;已失效，分解为ISO-4。&lt;br&gt;&lt;/font&gt;在脱离战斗12秒后，每秒恢复35点生命值。</str>
    <str key="4273980861" type="ucdt">纳能奥星假日帽。&lt;br&gt;&lt;font color="#2af72a"&gt;穿戴后经验加成+50%&lt;/font&gt;&lt;br&gt;&lt;font color="#FF0000"&gt;此物品只能在寒冬节日季期间使用。&lt;/font&gt;</str>
    <str key="4274027292" type="ucdt">VHO反射型（2倍）-黄点</str>
    <str key="4274083960" type="ucdt">C-4：金质勋章</str>
    <str key="4274172618" type="ucdt">返回前线</str>
    <str key="4274322701" type="ucdt">网络质量</str>
    <str key="4274370370" type="ucdt">突袭者轮毂罩25</str>
    <str key="4274450829" type="ucdt">兴奋剂注射器</str>
    <str key="4274610395" type="ucdt">完成一次资源警报</str>
    <str key="4274674650" type="ucdt">ACE工具 - 炮台：金质勋章</str>
    <str key="4274792830" type="ugdt">A.S.P. Operative Decal</str>
    <str key="4274950550" type="ucdt">在你的护甲上添加荆棘迷彩图案。仅限瓦努主权国使用。</str>
    <str key="4275130181" type="ucdt">玛奥科技工厂已被[*faction*]占领。</str>
    <str key="4275137765" type="ucdt">弹药携带量 8</str>
    <str key="4275650452" type="ucdt">载具补充弹药可以自动完成，你只需要在补给点旁边等候就可以了。</str>
    <str key="4275731528" type="ucdt">征服任何大陆</str>
    <str key="4275926834" type="ucdt">离线</str>
    <str key="4275947547" type="ucdt">抢救 5</str>
    <str key="4276104244" type="ucdt">奥星圣诞树</str>
    <str key="4276112674" type="ucdt">地球共和国渗透兵狙击步枪分组描述</str>
    <str key="4276129068" type="ucdt">开启后5秒内可以修复载具15%的耐久。如果启用此装置时载具已经着火，可以立即扑灭火焰。每30秒可以启用一次。</str>
    <str key="4276225684" type="ucdt">看来现在短路并爆炸的几率降低了75%！仅限地球共和国使用。</str>
    <str key="4276297594" type="ugdt">Wales Vehicle Decal</str>
    <str key="4276406779" type="ucdt">无人侦察机小队观察奖励</str>
    <str key="4276479511" type="ucdt">MH2反射瞄具（2倍）-共和国</str>
    <str key="4276542930" type="ucdt">自动获得</str>
    <str key="4276796847" type="ucdt">2015假日倒计时特卖第14天</str>
    <str key="4276911805" type="ugdt">Liberator Phantom Plating</str>
    <str key="4276924151" type="ucdt">处女座：金质勋章</str>
    <str key="4276993494" type="ucdt">堡垒部件伤害</str>
    <str key="4277101543" type="ugdt">IR SMOKE</str>
    <str key="4277190505" type="ucdt">雷击头盔</str>
    <str key="4277280852" type="ugdt">Rocklet Rifle</str>
    <str key="4277289965" type="ucdt">快速聊天 9</str>
    <str key="4277323328" type="ucdt">TRAC-5（点射版）：铜质勋章</str>
    <str key="4277329638" type="ucdt">基地武器迷彩</str>
    <str key="4277345201" type="ucdt">你方阵营可以通过载具终端购买载具。载具会随后出现在基地的庭院里。</str>
    <str key="4277362268" type="ucdt">转轮卡宾枪</str>
    <str key="4277960932" type="ucdt">A.S.P.返还券</str>
    <str key="4278052921" type="ugdt">Sicarius Mask</str>
    <str key="4278076062" type="ucdt">破坏发电机任务描述</str>
    <str key="4278078506" type="ucdt">你必须重新加入[*channel*]频道才能在里面发言。输入/joinchannel查看详细信息。</str>
    <str key="4278217575" type="ucdt">创建军团</str>
    <str key="4278562092" type="ucdt">中士炫光条纹</str>
    <str key="4278610663" type="ucdt">光子空对空导弹舱：银质勋章</str>
    <str key="4278636264" type="ucdt">摧毁了敌人的“火花”一辆。</str>
    <str key="4278671496" type="ucdt">激活一台修理无人机，它会在附近悬浮。10米内的友方载具、装备和MAX机甲单位每秒被动恢复46点生命值。冷却时间45秒。&lt;font color="#dc9c36"&gt;&lt;br&gt;&lt;br&gt;同一时间只能激活一台无人机。它会在你进入载具时损坏。该物品将在战役结束时失效。&lt;/font&gt;</str>
    <str key="4278766523" type="ucdt">英诺华占坑标题43</str>
    <str key="4278815763" type="ugdt">Paladin Helmet</str>
    <str key="4278991024" type="ucdt">飞鹰：铜质勋章</str>
    <str key="4279084329" type="ugdt">Warrior Plating</str>
    <str key="4279197929" type="ucdt">&lt;font color="#ACE1E5"&gt;&lt;u&gt;堡垒备战&lt;/u&gt;&lt;/font&gt;&lt;br&gt;重建堡垒舰队航母的结构完整性，准备从轨道再入大气层。&lt;br&gt;需要远征物资制造权限。&lt;font color="#CC200D"&gt;&lt;br&gt;&lt;br&gt;召唤堡垒舰队航母的必要条件。&lt;/font&gt;</str>
    <str key="4279204087" type="ugdt">Mosquito Bloodwasp Cockpit</str>
    <str key="4279224139" type="ucdt">前线护甲迷彩</str>
    <str key="4279327881" type="ucdt">为徘徊者加装炫光镶边。仅限地球共和国使用。</str>
    <str key="4279333564" type="ucdt">个性化你的地面载具，加装金色的“S”车标</str>
    <str key="4279341995" type="ucdt">希尔赫斯.大型哨所.6</str>
    <str key="4279374437" type="ugdt">Wasp</str>
    <str key="4279527151" type="ucdt">&lt;font color="#00FFAA"&gt;故障的间谍无人机：&lt;/font&gt;报告，TerranTurboRanger。下载已完成30%。继续防止打断。</str>
    <str key="4279661834" type="ucdt">韩国载具贴花</str>
    <str key="4279805415" type="ugdt">TR: Heavy Pistol 涂装</str>
    <str key="4279857796" type="ucdt">在你的护甲上添加添加岩石苔藓迷彩图案。仅限新联邦使用。</str>
    <str key="4279897635" type="ucdt">在你的护甲上添加一次性的因达尔海床迷彩图案。仅限瓦努主权国使用。一次性迷彩只能在本角色的一套配置中应用一次。</str>
    <str key="4279961313" type="ucdt">击落一架敌机</str>
    <str key="4279982363" type="ucdt">武器的装弹时间减少0.1秒。</str>
    <str key="4280117780" type="ucdt">知识库</str>
    <str key="4280151930" type="ucdt">驾驶载具时，在乘客击杀敌人时获得进度。</str>
    <str key="4280187347" type="ucdt">为你的角色添加水晶迷彩图案。仅限瓦努主权国使用。</str>
    <str key="4280210831" type="ugdt">决裂者金色侦察卫兵</str>
    <str key="4280249090" type="ucdt">进一步加快渗透兵破解控制台的速度。</str>
    <str key="4280345657" type="ucdt">2倍变焦瞄具</str>
    <str key="4280523601" type="ucdt">实验型的“鞭笞者”X2可以发射活性等离子球，命中目标时爆炸。现场试验显示此武器在火力压制，逼出角落敌军和杀伤步兵方面有奇效。仅限瓦努主权国使用。</str>
    <str key="4280557613" type="ucdt">Tech Planet Swap FX NPC</str>
    <str key="4280561362" type="ucdt">使用近战武器击杀敌人可回复生命值。</str>
    <str key="4280605587" type="ucdt">按[%s]键使用飞机终端</str>
    <str key="4280878833" type="ucdt">竞速者高速底盘 2</str>
    <str key="4280910276" type="ucdt">所有非MAX职业均可装备。所有阵营均可使用此物品。</str>
    <str key="4281197716" type="ucdt">外置式弹仓 5</str>
    <str key="4281217299" type="ucdt">纳米网专家 5</str>
    <str key="4281390741" type="ucdt">为你的载具添加贴花。仅限地球共和国使用。</str>
    <str key="4281410542" type="ucdt">获取消耗型的医疗注射器，使用后能立即为玩家回复生命值。</str>
    <str key="4281610168" type="ucdt">武器能够携带的最大弹药数量增加350发。</str>
    <str key="4281743765" type="ucdt">悟空载具贴花</str>
    <str key="4281914033" type="ucdt">Phoenix Group军团贴花</str>
    <str key="4281996873" type="ucdt">女武神蓝色XW炫光镶边</str>
    <str key="4282001505" type="ucdt">自己人，别开枪</str>
    <str key="4282338803" type="ucdt">法国贩毒网载具贴花</str>
    <str key="4282496697" type="ugdt">Wasp Rebreather Helmet</str>
    <str key="4282547819" type="ucdt">保卫友军基地</str>
    <str key="4282569082" type="ugdt">Gold Weapon Camo</str>
    <str key="4282733233" type="ugdt">Hazard Shielding II</str>
    <str key="4282746137" type="ucdt">宙斯盾方阵炮台：银质勋章</str>
    <str key="4282880197" type="ucdt">训练：各就各位</str>
    <str key="4282897751" type="ucdt">防爆护甲</str>
    <str key="4282934802" type="ucdt">橙色Chimera底盘灯光</str>
    <str key="4282986295" type="ucdt">纳能网生成器回满能量的耗时缩短到20秒。</str>
    <str key="4282988241" type="ucdt">载具的生命值总量提升23%。</str>
    <str key="4283146762" type="ugdt">弹药包 3</str>
    <str key="4283243091" type="ucdt">心动折扣，尽享最热销火花武器！</str>
    <str key="4283434146" type="ucdt">解锁并强化轻型突击兵喷射背包的多种能力。技能可在配置界面进行装备。</str>
    <str key="4283670689" type="ucdt">决裂者贴花</str>
    <str key="4283712712" type="ucdt">先驱正面护盾 4</str>
    <str key="4283811655" type="ugdt">NS-61 "Networked" Emissary</str>
    <str key="4283811912" type="ucdt">**Test for Localization**</str>
    <str key="4283830745" type="ucdt">快速部署已禁用</str>
    <str key="4283884594" type="ucdt">默认弹匣的弹药容量增加10发。</str>
    <str key="4284160659" type="ucdt">中尉 3</str>
    <str key="4284245813" type="ucdt">NC6S高斯SAW（可调版）：铜质勋章</str>
    <str key="4284308150" type="ucdt">亡魂 1</str>
    <str key="4284418151" type="ucdt">分解重复插件</str>
    <str key="4284455121" type="ucdt">NiSGO（3.4倍）</str>
    <str key="4284528264" type="ucdt">瑰露ACOG适用于中距离交战。这款瞄具的放大倍率是3.4倍。</str>
    <str key="4284705753" type="ucdt">防火墙 2</str>
    <str key="4284967526" type="ucdt">证书附件描述</str>
    <str key="4285047299" type="ucdt">女武神青色XW炫光镶边</str>
    <str key="4285207559" type="ucdt">武器能够携带的最大弹药数量增加300发。</str>
    <str key="4285307048" type="ucdt">女武神NS-C喇叭</str>
    <str key="4285407112" type="ugdt">Heavyweight 5</str>
    <str key="4285594750" type="ucdt">蹲姿的移动速度惩罚降低55%。</str>
    <str key="4285710052" type="ucdt">AF-4A强盗：铜质勋章</str>
    <str key="4285780919" type="ucdt">将对轨道轰击伤害的抵抗能力由30%增加到44%。此外，在未部署时，载具将不再受到来自轨道轰击以及其他武器的物理冲击的影响。</str>
    <str key="4285831499" type="ucdt">E540长戟：银质勋章</str>
    <str key="4285835688" type="ucdt">LA1巨锚：铜质勋章</str>
    <str key="4285850947" type="ucdt">守住控制中心!</str>
    <str key="4285854699" type="ucdt">在你的载具上添加一次性沙漠灌木V1迷彩图案。仅限地球共和国使用。一次性迷彩只能在本角色的一套配置中应用一次。</str>
    <str key="4285969774" type="ucdt">按住[%s]解锁储物柜</str>
    <str key="4286030418" type="ucdt">打开后，在载具后座周围生成铁血护盾，保护乘客免受炮火的直接袭击。护盾受到损害的同时会消耗能量，关闭后或能量降为零时将降下护盾。能量会在护盾降下后逐渐恢复并于35秒内完全充满。只有当能量储备大于25%时，才能重新打开护盾</str>
    <str key="4286085624" type="ucdt">标枪小队观察奖励</str>
    <str key="4286172061" type="ucdt">你的护盾重新充能的延时缩短0.6秒。此外，每当你的护盾耗尽破裂，你的冲刺速度会提高20%，持续3.5秒。&lt;font color="#dc9c36"&gt;触发后有12秒冷却时间。&lt;/font&gt;</str>
    <str key="4286310720" type="ucdt">职业配置</str>
    <str key="4286369154" type="ucdt">电线载具迷彩</str>
    <str key="4286443923" type="ugdt">O2-8 (8x)</str>
    <str key="4286548080" type="ugdt">Lance Cpl. 2 涂装</str>
    <str key="4286690992" type="ucdt">当处于雷暴中时，你可以通过将风暴能量转化成涡轮燃料来分流过多的风暴能量。&lt;font color="#dc9c36"&gt;&lt;br&gt;&lt;br&gt;该物品将在战役结束时失效。&lt;/font&gt;</str>
    <str key="4286704086" type="ucdt">突击步枪大师背景横幅</str>
    <str key="4286855232" type="ucdt">启示者头盔</str>
    <str key="4287034421" type="ucdt">证书附件描述</str>
    <str key="4287101501" type="ucdt">《行星边际》15周年</str>
    <str key="4287108012" type="ucdt">你每秒会自动恢复6%生命值。受到伤害后8秒内无法进行自动修复。</str>
    <str key="4287130820" type="ucdt">雪色白杨林迷彩礼包</str>
    <str key="4287161133" type="ucdt">火花橙色照明球</str>
    <str key="4287171865" type="ucdt">轻捷而致命，SX45“传令兵”作为佩枪有着强大的杀伤力。</str>
    <str key="4287227121" type="ucdt">解放者机首炮</str>
    <str key="4287427772" type="ucdt">地球共和国重武器生命等级1</str>
    <str key="4287456466" type="ucdt">奥星毁灭者：铜质勋章</str>
    <str key="4287510257" type="ucdt">我们已经接到通知，称你有所发现。现在请继续进行回收作业。</str>
    <str key="4287857467" type="ucdt">将海盗战机的获取时间间隔减少120秒。</str>
    <str key="4287983351" type="ucdt">添加好友</str>
    <str key="4288008458" type="ugdt">金色死者笑脸车标</str>
    <str key="4288080891" type="ucdt">v0.2.9</str>
    <str key="4288125705" type="ucdt">兴奋剂注射器</str>
    <str key="4288179164" type="ucdt">载具在生成时携带6500 Cortium，而非5000。</str>
    <str key="4288287388" type="ucdt">在你的武器上添加因达尔沙丘迷彩图案。所有阵营均可使用此装备。</str>
    <str key="4288415074" type="ucdt">陆龟：金质勋章</str>
    <str key="4288423596" type="ucdt">武器能够携带的最大弹药数量增加120发。</str>
    <str key="4288450598" type="ucdt">增强型的天琴座反射倍镜能在近距离交火中提供清晰的视野，也具有足够的放大倍率，从而在中距离保持精准。</str>
    <str key="4288526789" type="ucdt">在你的护甲上添加一次性沙地灌木迷彩图案。仅限地球共和国使用。一次性迷彩只能在本角色的一套配置中应用一次。</str>
    <str key="4288588534" type="ugdt">Pistol Packin' Mama Armor Decal</str>
    <str key="4288806766" type="ucdt">敌方锁定此载具所需的时间增加1秒，并防止载具在敌人小地图上被自动侦测到。</str>
    <str key="4288818804" type="ucdt">洪流</str>
    <str key="4289019450" type="ucdt">社交：青铜</str>
    <str key="4289255620" type="ucdt">BDS（6倍）</str>
    <str key="4289308398" type="ucdt">伊卡洛斯喷射背包 2</str>
    <str key="4289432569" type="ucdt">炫目条纹武器迷彩</str>
    <str key="4289754738" type="ucdt">资源加成 - 3天</str>
    <str key="4289776838" type="ugdt">重金属</str>
    <str key="4289787395" type="ucdt">&lt;font color="#00FFAA"&gt;先遣远征代表：&lt;/font&gt;根据我们的记录，目前你似乎没有足够的权限进行交易。</str>
    <str key="4289808493" type="ugdt">刀锋迷彩</str>
    <str key="4289923593" type="ucdt">工程兵</str>
    <str key="4290109991" type="ucdt">领土</str>
    <str key="4290164652" type="ucdt">VS MAX背景横幅</str>
    <str key="4290607389" type="ucdt">奈克瑟斯占据领土</str>
    <str key="4290848811" type="ugdt">Lightning Adeptus Plating</str>
    <str key="4290867139" type="ucdt">在你的武器上添加艾美瑞什森林V2迷彩图案。所有阵营均可使用此装备。</str>
    <str key="4290908158" type="ucdt">瓦努主权国十字载具贴花</str>
    <str key="4290936301" type="ugdt">NSX "Ivory" Naginata</str>
    <str key="4290947219" type="ucdt">由于敌军一直在炮击我们的前沿基地，我们的部队急需弹药。 我们正在召集所有Galaxy飞行员，装备完毕后飞往争夺区域为你们的前线进行补给。</str>
    <str key="4291022264" type="ucdt">装弹速度 1</str>
    <str key="4291183215" type="ucdt">要塞安全了！</str>
    <str key="4291201214" type="ucdt">M40暴怒：金质勋章</str>
    <str key="4291242566" type="ucdt">此大陆已被封锁。若想解锁此大陆，则必须先封锁其他大陆。</str>
    <str key="4291332761" type="ucdt">开启后，你将不会再收到小队邀请。</str>
    <str key="4291338812" type="ucdt">利用纳能持续进行修理，每5秒修复4%的耐久。受到伤害后12秒内无法进行自动修复。</str>
    <str key="4291430343" type="ucdt">前往Esamir东北部的新异常。</str>
    <str key="4291531149" type="ucdt">炮手击杀共享 - 步兵</str>
    <str key="4291558743" type="ucdt">你可以使用火箭筒，或者其他更为强大的武器来应对这些威胁。</str>
    <str key="4291584324" type="ucdt">其他</str>
    <str key="4291692771" type="ucdt">为你的载具添加贴花。仅限地球共和国使用。</str>
    <str key="4291762753" type="ugdt">NSX "Networked" Yumi</str>
    <str key="4291796823" type="ucdt">复苏促销礼包</str>
    <str key="4291858712" type="ucdt">伊萨米尔</str>
    <str key="4291899957" type="ugdt">心宿二LC</str>
    <str key="4291979905" type="ucdt">MG-A1劲弩：银质勋章</str>
    <str key="4292062856" type="ucdt">火箭筒可以强力杀伤敌方载具。</str>
    <str key="4292484731" type="ucdt">&lt;font color="#ACE1E5"&gt;&lt;u&gt;使用&lt;/u&gt;&lt;/font&gt;&lt;br&gt;到庇护所的先遣远征代表处的托兰那里领取奖励。&lt;br&gt;&lt;br&gt;&lt;font color="#ACE1E5"&gt;&lt;u&gt;说明&lt;/u&gt;&lt;/font&gt;&lt;br&gt;需要远征物资制造权限。&lt;br&gt;&lt;br&gt;派遣一次远征，为你的军团武器库收集&lt;font color="#C963CD"&gt;聚合星烬&lt;/font&gt;。可能收获15到21点&lt;font color="#C963CD"&gt;聚合星烬&lt;/font&gt;。&lt;font color="#CC200D"&gt;&lt;br&gt;&lt;br&gt;同一时间只能派遣“一次”资源远征。&lt;/font&gt;</str>
    <str key="4292710072" type="ucdt">用20点&lt;font color="#C963CD"&gt;聚合星烬&lt;/font&gt;换取88点&lt;font color="#5CA8DD"&gt;合成源液&lt;/font&gt;。&lt;font color="#CC200D"&gt;&lt;br&gt;&lt;br&gt;使用军团武器库中的资源。&lt;/font&gt;</str>
    <str key="4292871303" type="ucdt">医疗兵超级MHS头盔</str>
    <str key="4292880689" type="ucdt">火花黄色照明球</str>
    <str key="4292925555" type="ucdt">龙腾</str>
    <str key="4292929690" type="ucdt">红色长颈鹿迷彩</str>
    <str key="4292971251" type="ucdt">武器的装弹时间减少0.36秒。</str>
    <str key="4293098752" type="ucdt">解锁PMG-200和全套附件。仅供NSO使用。</str>
    <str key="4293283133" type="ucdt">我们需要坦克操作员去战场上对抗敌人的装甲部队，特别是给我们带来不少麻烦的新型Chimera。挑选一辆Vanguard，把他们的新坦克打成废铁吧。</str>
    <str key="4293429241" type="ugdt">NC粗鲁语音包</str>
    <str key="4293508556" type="ucdt">将炮台每次开火后的冷却时间减少至5.25秒。</str>
    <str key="4293862761" type="ucdt">天顶星VX-5：金质勋章</str>
    <str key="4294107292" type="ucdt">火花保险杠TR006描述</str>
    <str key="4294296469" type="ucdt">按住[%s]提取数据</str>
    <str key="4294296787" type="ucdt">XM98：银质勋章</str>
    <str key="4294299871" type="ucdt">开球迷彩</str>
    <str key="4294348009" type="ugdt">Hossin Digital Scrub Camo</str>
    <str key="4294561621" type="ucdt">侦察兵载具迷彩</str>
    <str key="4294666626" type="ucdt">艾美瑞什南方折跃门</str>
    <str key="4294804731" type="ucdt">虽然与这头盔命名的时代相比，战争的残忍不曾减少半分，但至少变得不那么不堪入目了。仅供[#VS#]使用。</str>
</root>
