<?xml version="1.0" encoding="UTF-8"?>

<root>
  <str key="661996069-ucdt" type="ucdt" originalKey="661996069">NS-61 “戰時” 密使</str>
  <str key="746949302-ugdt" type="ugdt" originalKey="746949302">NS-61 “戰時” 密使</str>
  <str key="1124462279-ugdt" type="ugdt" originalKey="1124462279">WARx（2 倍）</str>
  <str key="1217715747-ucdt" type="ucdt" originalKey="1217715747">為你的奇美拉加裝外飾板。僅限納能特工使用。</str>
  <str key="1291811998-ucdt" type="ucdt" originalKey="1291811998">夏日活動的尾聲</str>
  <str key="1650706537-ucdt" type="ucdt" originalKey="1650706537">NS-61 “戰時” 密使 金質勳章</str>
  <str key="1725140450-ucdt" type="ucdt" originalKey="1725140450">NS-61 “戰時” 密使 銅質勳章</str>
  <str key="1794870098-ucdt" type="ucdt" originalKey="1794870098">步兵裝備、迷彩和載具裝備優惠！</str>
  <str key="2173688428-ucdt" type="ucdt" originalKey="2173688428">WARx（2 倍）</str>
  <str key="2244841719-ugdt" type="ugdt" originalKey="2244841719">WARx（1 倍）</str>
  <str key="2247792035-ucdt" type="ucdt" originalKey="2247792035">自然僞裝</str>
  <str key="2682788684-ugdt" type="ugdt" originalKey="2682788684">自然僞裝</str>
  <str key="3082684709-ucdt" type="ucdt" originalKey="3082684709">NS-61 “戰時” 密使 銀質勳章</str>
  <str key="3277614595-ucdt" type="ucdt" originalKey="3277614595">消音器</str>
  <str key="3281859168-ucdt" type="ucdt" originalKey="3281859168">抑製武器發出的噪音，削弱槍口的火光，射擊時敵人將無法在小地圖上看到你的位置。同時武器傷害衰減距離提前 20 米，子彈速度降低 15%。</str>
  <str key="3361426618-ucdt" type="ucdt" originalKey="3361426618">NS-61 “戰時” 密使 奧星勳章</str>
  <str key="3729718410-ucdt" type="ucdt" originalKey="3729718410">NS-61 “戰時” 密使 綬帶</str>
  <str key="3972700557-ucdt" type="ucdt" originalKey="3972700557">WARx（1 倍）</str>
  <str key="3980934886-ucdt" type="ucdt" originalKey="3980934886">非凡 VIII</str>
  <str key="4007381370-ucdt" type="ucdt" originalKey="4007381370">&lt;font size="25" color="#ACE1E5"&gt;夏日時光或許即將結束，但歡樂並未隨之消失。&lt;/font&gt;&lt;br&gt;&lt;br&gt;&lt;font size="22" color="#ACE1E5"&gt;周年禮包與社區禮包返場 &lt;/font&gt;&lt;br&gt;&lt;font color="#ACE1E5"&gt; &amp;#8226;&lt;/font&gt; 7、8、9 與 10 周年禮包&lt;br&gt;&lt;font color="#ACE1E5"&gt; &amp;#8226;&lt;/font&gt; 北極戰爭禮包&lt;br&gt;&lt;font color="#ACE1E5"&gt; &amp;#8226;&lt;/font&gt; 變節者禮包&lt;br&gt;&lt;br&gt;&lt;font size="22" color="#ACE1E5"&gt; 季節性禮包回歸&lt;/font&gt;&lt;br&gt;&lt;font color="#ACE1E5"&gt; &amp;#8226;&lt;/font&gt; 雙星交匯禮包&lt;br&gt;&lt;font color="#ACE1E5"&gt; &amp;#8226;&lt;/font&gt; 農曆新年禮包&lt;br&gt;&lt;font color="#ACE1E5"&gt; &amp;#8226;&lt;/font&gt; 新的開始禮包&lt;br&gt;&lt;br&gt;&lt;font size="22" color="#ACE1E5"&gt; 還有飾品六折優惠！ &lt;/font&gt;&lt;br&gt;&lt;font color="#ACE1E5"&gt; &amp;#8226;&lt;/font&gt; 步兵飾品&lt;br&gt;&lt;font color="#ACE1E5"&gt; &amp;#8226;&lt;/font&gt; 載具飾品&lt;br&gt;&lt;font color="#ACE1E5"&gt; &amp;#8226;&lt;/font&gt; 迷彩</str>
</root>
