<?xml version="1.0" encoding="UTF-8"?>

<root>
  <str key="17071003-ucdt" type="ucdt" originalKey="17071003">NS-44 "Primed Amethyst" Commissioner: Copper Medal</str>
  <str key="19818206-ucdt" type="ucdt" originalKey="19818206">11-Year Loyalty Banner</str>
  <str key="91694418-ucdt" type="ucdt" originalKey="91694418">NS-R3 "Mountain Buster" Swarm: Auraxium Medal</str>
  <str key="99176759-ucdt" type="ucdt" originalKey="99176759">Molten Fury Armor</str>
  <str key="251435109-ucdt" type="ucdt" originalKey="251435109">Geologist's Eleventh-Year Anniversary Bundle</str>
  <str key="297331717-ugdt" type="ugdt" originalKey="297331717">Dissonant Resonator Helmet</str>
  <str key="303602719-ugdt" type="ugdt" originalKey="303602719">Ice Dragon Helmet</str>
  <str key="305787710-ucdt" type="ucdt" originalKey="305787710">Invaluable Operator Armor</str>
  <str key="359711154-ugdt" type="ugdt" originalKey="359711154">NS "Fortune" Decimator</str>
  <str key="458466658-ugdt" type="ugdt" originalKey="458466658">Seismic Surveyor Drop Pod</str>
  <str key="461396387-ucdt" type="ucdt" originalKey="461396387">Fortune Seeker HLX: Auraxium Medal</str>
  <str key="463501796-ugdt" type="ugdt" originalKey="463501796">Geodescent Lumifiber Trim</str>
  <str key="486762512-ucdt" type="ucdt" originalKey="486762512">Celebrate eleven years of PlanetSide 2 with this special bundle. Note: Bundle contains a weapon and cosmetics for VS/NC/TR/NSO empires.</str>
  <str key="497234775-ucdt" type="ucdt" originalKey="497234775">NS-R3 "Mountain Buster" Swarm: Gold Medal</str>
  <str key="515533606-ucdt" type="ucdt" originalKey="515533606">NS-44 "Primed Amethyst" Commissioner</str>
  <str key="543144384-ucdt" type="ucdt" originalKey="543144384">NS "Fortune" Decimator: Gold Medal</str>
  <str key="662122004-ucdt" type="ucdt" originalKey="662122004">11-Year Loyalty Banner Frame</str>
  <str key="807947935-ucdt" type="ucdt" originalKey="807947935">Title: Nascent Envoy</str>
  <str key="876802119-ugdt" type="ugdt" originalKey="876802119">Zeal Infuser Armor</str>
  <str key="914638709-ugdt" type="ugdt" originalKey="914638709">Volcanic Glass Helmet</str>
  <str key="1021496496-ucdt" type="ucdt" originalKey="1021496496">Rock Hound's Eleventh-Year Anniversary Bundle</str>
  <str key="1116890022-ucdt" type="ucdt" originalKey="1116890022">Dissonant Resonator Helmet</str>
  <str key="1216726623-ucdt" type="ucdt" originalKey="1216726623">NS "Fortune" Decimator: Silver Medal</str>
  <str key="1218390521-ucdt" type="ucdt" originalKey="1218390521">NS-R3 "Mountain Buster" Swarm: Silver Medal</str>
  <str key="1223518971-ucdt" type="ucdt" originalKey="1223518971">Ice Dragon Helmet</str>
  <str key="1239587872-ugdt" type="ugdt" originalKey="1239587872">11-Year Loyalty Banner Frame</str>
  <str key="1266369895-ugdt" type="ugdt" originalKey="1266369895">NS-44 "Primed Amethyst" Commissioner</str>
  <str key="1297661106-ucdt" type="ucdt" originalKey="1297661106">NS-R3 "Mountain Buster" Swarm</str>
  <str key="1302962790-ucdt" type="ucdt" originalKey="1302962790">Happy 11-Year Anniversary!</str>
  <str key="1451337019-ucdt" type="ucdt" originalKey="1451337019">NS "Fortune" Decimator: Copper Medal</str>
  <str key="1629981379-ucdt" type="ucdt" originalKey="1629981379">NS-44 "Primed Amethyst" Commissioner: Auraxium Medal</str>
  <str key="1665288504-ugdt" type="ugdt" originalKey="1665288504">Volcanic Geode Armor</str>
  <str key="1672862116-ugdt" type="ugdt" originalKey="1672862116">Molten Fury Helmet</str>
  <str key="1727041231-ucdt" type="ucdt" originalKey="1727041231">Hobbyist's Eleventh-Year Anniversary Bundle</str>
  <str key="1727751659-ucdt" type="ucdt" originalKey="1727751659">Geodescent Lumifiber Trim</str>
  <str key="1792629550-ucdt" type="ucdt" originalKey="1792629550">Celebrate 11 years of war on Auraxis with these special items!</str>
  <str key="1988577601-ucdt" type="ucdt" originalKey="1988577601">Fortune Seeker HLX: Copper Medal</str>
  <str key="2075637735-ucdt" type="ucdt" originalKey="2075637735">Seismic Surveyor Drop Pod</str>
  <str key="2174589540-ucdt" type="ucdt" originalKey="2174589540">Celebrating 11 years of war on Auraxis!</str>
  <str key="2193834651-ugdt" type="ugdt" originalKey="2193834651">Title: Nascent Envoy</str>
  <str key="2226436756-ucdt" type="ucdt" originalKey="2226436756">Molten Fury Helmet</str>
  <str key="2247338416-ucdt" type="ucdt" originalKey="2247338416">NS "Fortune" Decimator: Auraxium Medal</str>
  <str key="2639707070-ucdt" type="ucdt" originalKey="2639707070">Fortune Seeker HLX: Silver Medal</str>
  <str key="2644483562-ucdt" type="ucdt" originalKey="2644483562">Volcanic Glass Helmet</str>
  <str key="2680419743-ucdt" type="ucdt" originalKey="2680419743">Celebrate eleven years of PlanetSide 2 with this bundle. Note: Bundle contains cosmetics for VS/NC/TR/NSO empires.  Heroic Boost is granted only to the character that purchases the bundle.</str>
  <str key="2720912039-ucdt" type="ucdt" originalKey="2720912039">Grants the "Nascent Envoy" prefix title.</str>
  <str key="2756541602-ucdt" type="ucdt" originalKey="2756541602">NS "Fortune" Decimator</str>
  <str key="2769898810-ugdt" type="ugdt" originalKey="2769898810">Invaluable Operator Armor</str>
  <str key="2804541529-ucdt" type="ucdt" originalKey="2804541529">Fortune Seeker HLX: Gold Medal</str>
  <str key="2957126185-ucdt" type="ucdt" originalKey="2957126185">NS-44 "Primed Amethyst" Commissioner: Silver Medal</str>
  <str key="2983332872-ucdt" type="ucdt" originalKey="2983332872">Zeal Infuser Armor</str>
  <str key="3082993305-ucdt" type="ucdt" originalKey="3082993305">NS-44 "Primed Amethyst" Commissioner: Gold Medal</str>
  <str key="3083070890-ucdt" type="ucdt" originalKey="3083070890">Fortune Seeker HLX</str>
  <str key="3113225140-ugdt" type="ugdt" originalKey="3113225140">11-Year Loyalty Banner</str>
  <str key="3154690240-ugdt" type="ugdt" originalKey="3154690240">Molten Fury Armor</str>
  <str key="3316762487-ugdt" type="ugdt" originalKey="3316762487">Dissonant Resonator Armor</str>
  <str key="3348027698-ugdt" type="ugdt" originalKey="3348027698">Invaluable Operator Helmet</str>
  <str key="3355769059-ugdt" type="ugdt" originalKey="3355769059">NS-R3 "Mountain Buster" Swarm</str>
  <str key="3489279568-ucdt" type="ucdt" originalKey="3489279568">Zeal Infuser Helmet</str>
  <str key="3573915410-ucdt" type="ucdt" originalKey="3573915410">With the holiday season fast approaching, here are some of the highlights of this anniversary update:&lt;ul&gt;&lt;li&gt;&lt;font size="28" color="#ACE1E5"&gt;Outfit Wars: Nexus Season 2&lt;/font&gt; - Outfit Wars: Nexus returns for Season 2!  Now with a lowered minimum entry requirement of 24 players.  Does your outfit have what it takes to reach the top?&lt;/li&gt;&lt;li&gt;&lt;font size="28" color="#ACE1E5"&gt;Oshur Updates&lt;/font&gt; - Converted 2 bases from Construction Outposts into single Capture Point Outposts at Veridad Pass and Astira Solar Station!  Oh and two dog tags have changed location, so best update that wiki...when you find them!&lt;/li&gt;&lt;li&gt;&lt;font size="28" color="#ACE1E5"&gt;11 Year Anniversary Bundles!&lt;/font&gt; - Shine bright this anniversary with the Hobbyist, Geologist and Rock Hound anniversary bundles in the Depot!&lt;/li&gt;&lt;br&gt;Visit planetside2.com for the full patch notes.</str>
  <str key="3778695340-ugdt" type="ugdt" originalKey="3778695340">Zeal Infuser Helmet</str>
  <str key="3844808675-ucdt" type="ucdt" originalKey="3844808675">Volcanic Geode Armor</str>
  <str key="3859668596-ucdt" type="ucdt" originalKey="3859668596">Invaluable Operator Helmet</str>
  <str key="3873810473-ucdt" type="ucdt" originalKey="3873810473">NEXUS SEASON 2</str>
  <str key="3906441192-ucdt" type="ucdt" originalKey="3906441192">Sparkle and shine with the Limited Edition "Primed Amethyst" variant of the accurate NS-44 Commissioner revolver!  All factions can use this weapon.</str>
  <str key="3942696329-ugdt" type="ugdt" originalKey="3942696329">11-Years of Loyalty</str>
  <str key="3945179590-ucdt" type="ucdt" originalKey="3945179590">Dissonant Resonator Armor</str>
  <str key="3979164333-ucdt" type="ucdt" originalKey="3979164333">11-Years of Loyalty</str>
  <str key="4005733673-ucdt" type="ucdt" originalKey="4005733673">Encase yourself with this geode themed trim!  This won't stop you from shining bright like a...precious stone! &lt;font color="#dc9c36"&gt;Color of trim changes based on your current faction.&lt;/font&gt;</str>
  <str key="4057192145-ugdt" type="ugdt" originalKey="4057192145">Fortune Seeker HLX</str>
  <str key="4129410529-ucdt" type="ucdt" originalKey="4129410529">NS-R3 "Mountain Buster" Swarm: Copper Medal</str>
  <str key="4231899096-ucdt" type="ucdt" originalKey="4231899096">Nascent Envoy</str>
  <str key="4266599631-ucdt" type="ucdt" originalKey="4266599631">Celebrate eleven years of PlanetSide 2 with this massive bundle. Note: Bundle contains weapons and cosmetics for VS/NC/TR/NSO empires. Heroic Boost is granted only to the character that purchases the bundle.</str>
</root>
